igeDlibExtern.cp37-win32.pyd
igeDlibExtern-0.0.1.dist-info/LICENSE
igeDlibExtern-0.0.1.dist-info/METADATA
igeDlibExtern-0.0.1.dist-info/WHEEL
igeDlibExtern-0.0.1.dist-info/top_level.txt
igeDlibExtern-0.0.1.dist-info/RECORD
